examples/__init__.py
examples/notify.py
examples/sync.py
ricsdl/__init__.py
ricsdl/configuration.py
ricsdl/exceptions.py
ricsdl/syncstorage.py
ricsdl/syncstorage_abc.py
ricsdl/backend/__init__.py
ricsdl/backend/dbbackend_abc.py
ricsdl/backend/fake_dict_db.py
ricsdl/backend/redis.py
ricsdl-3.1.2.dist-info/LICENSES.txt
ricsdl-3.1.2.dist-info/METADATA
ricsdl-3.1.2.dist-info/WHEEL
ricsdl-3.1.2.dist-info/top_level.txt
ricsdl-3.1.2.dist-info/RECORD
