Metadata-Version: 2.1
Name: ricsdl
Version: 3.1.2
Summary: Shared Data Layer (SDL) provides a high-speed interface to access shared storage
Home-page: https://gerrit.o-ran-sc.org/r/admin/repos/ric-plt/sdlpy
Author: Timo Tietavainen
Author-email: timo.tietavainen@nokia.com
License: Apache 2.0
Keywords: RIC SDL
Classifier: Development Status :: 4 - Beta
Classifier: Intended Audience :: Telecommunications Industry
Classifier: Programming Language :: Python :: 3
Classifier: Programming Language :: Python :: 3.7
Classifier: License :: OSI Approved :: Apache Software License
Classifier: Operating System :: POSIX :: Linux
Requires-Python: >=3.7
License-File: LICENSES.txt
Requires-Dist: setuptools
Requires-Dist: redis (==4.1.1)
Requires-Dist: hiredis (==2.0.0)
